odoo/addons/pos_order_remove_line/README.rst
odoo/addons/pos_order_remove_line/__init__.py
odoo/addons/pos_order_remove_line/__manifest__.py
odoo/addons/pos_order_remove_line/i18n/it.po
odoo/addons/pos_order_remove_line/i18n/pos_order_remove_line.pot
odoo/addons/pos_order_remove_line/readme/CONTRIBUTORS.rst
odoo/addons/pos_order_remove_line/readme/DESCRIPTION.rst
odoo/addons/pos_order_remove_line/static/description/icon.png
odoo/addons/pos_order_remove_line/static/description/index.html
odoo/addons/pos_order_remove_line/static/src/css/orderline.scss
odoo/addons/pos_order_remove_line/static/src/js/orderline.js
odoo/addons/pos_order_remove_line/static/src/xml/orderline.xml
odoo/addons/pos_order_remove_line/views/assets.xml
odoo14_addon_pos_order_remove_line-14.0.1.0.1.dev5.dist-info/METADATA
odoo14_addon_pos_order_remove_line-14.0.1.0.1.dev5.dist-info/WHEEL
odoo14_addon_pos_order_remove_line-14.0.1.0.1.dev5.dist-info/top_level.txt
odoo14_addon_pos_order_remove_line-14.0.1.0.1.dev5.dist-info/RECORD
